rfcc/__init__.py
rfcc/data_ops.py
rfcc/model.py
rfcc/path_ops.py
rfcc-1.0.1.dist-info/LICENSE
rfcc-1.0.1.dist-info/METADATA
rfcc-1.0.1.dist-info/WHEEL
rfcc-1.0.1.dist-info/top_level.txt
rfcc-1.0.1.dist-info/RECORD
