Metadata-Version: 2.1
Name: rfcc
Version: 1.0.1
Summary: RFCC: Random Forest Consensus Clustering for Regression and Classification
Home-page: https://github.com/IngoMarquart/RFCC
Author: Ingo Marquart
Author-email: ingo.marquart@esmt.org
License: MIT
Platform: UNKNOWN
Requires-Dist: pandas
Requires-Dist: scipy
